clientz/__init__.py
clientz/core.py
clientz/log.py
clientz/server.py
clientz/utils.py
clientz-0.1.21.dist-info/METADATA
clientz-0.1.21.dist-info/WHEEL
clientz-0.1.21.dist-info/top_level.txt
clientz-0.1.21.dist-info/RECORD
