Metadata-Version: 2.4
Name: clientz
Version: 0.1.21
Summary: Add your description here
Requires-Python: >=3.10
Requires-Dist: fastapi>=0.115.12
Requires-Dist: llmada==1.0.3
Requires-Dist: querypipz==0.1.22
Requires-Dist: requests>=2.32.3
Requires-Dist: sse-starlette>=2.3.4
Requires-Dist: toml==0.10.2
Requires-Dist: uvicorn>=0.34.2
